nonebot_plugin_cesaa/__init__.py
nonebot_plugin_cesaa/py.typed
nonebot_plugin_cesaa/record.py
nonebot_plugin_cesaa/record.pyi
nonebot_plugin_cesaa-0.5.0.dist-info/METADATA
nonebot_plugin_cesaa-0.5.0.dist-info/WHEEL
nonebot_plugin_cesaa-0.5.0.dist-info/licenses/LICENSE
nonebot_plugin_cesaa-0.5.0.dist-info/RECORD
