Metadata-Version: 2.4
Name: nonebot-plugin-cesaa
Version: 0.5.0
Summary: 为 chatrecorder 添加 send-anything-anywhere 的 PlatformTarget 支持
Project-URL: Homepage, https://github.com/he0119/nonebot-plugin-chatrecorder-extension-send-anything-anywhere
Project-URL: Repository, https://github.com/he0119/nonebot-plugin-chatrecorder-extension-send-anything-anywhere.git
Project-URL: Issues, https://github.com/he0119/nonebot-plugin-chatrecorder-extension-send-anything-anywhere/issues
Project-URL: Changelog, https://github.com/he0119/nonebot-plugin-chatrecorder-extension-send-anything-anywhere/blob/main/CHANGELOG.md
Author-email: uy_sun <hmy0119@gmail.com>
License: MIT License
License-File: LICENSE
Requires-Python: >=3.9
Requires-Dist: nonebot-plugin-chatrecorder>=0.7.0
Requires-Dist: nonebot-plugin-send-anything-anywhere>=0.7.1
Requires-Dist: nonebot2>=2.2.0
